MANIFEST.in
README.rst
setup.py
src/ofxstatement/__init__.py
src/ofxstatement/plugins/__init__.py
src/ofxstatement/plugins/lansforsakringar.py
src/ofxstatement_lansforsakringar.egg-info/PKG-INFO
src/ofxstatement_lansforsakringar.egg-info/SOURCES.txt
src/ofxstatement_lansforsakringar.egg-info/dependency_links.txt
src/ofxstatement_lansforsakringar.egg-info/entry_points.txt
src/ofxstatement_lansforsakringar.egg-info/namespace_packages.txt
src/ofxstatement_lansforsakringar.egg-info/requires.txt
src/ofxstatement_lansforsakringar.egg-info/top_level.txt
src/ofxstatement_lansforsakringar.egg-info/zip-safe