Metadata-Version: 1.1
Name: ofxstatement-lansforsakringar
Version: 0.2.0
Summary: Länsförsäkringar plugin for ofxstatement
Home-page: https://github.com/lbschenkel/ofxstatement-lansforsakringar
Author: Leonardo Brondani Schenkel
Author-email: leonardo@schenkel.net
License: GPLv3
Keywords: ofx,banking,statement
Platform: UNKNOWN
Classifier: Development Status :: 4 - Beta
Classifier: Programming Language :: Python :: 3
Classifier: Natural Language :: English
Classifier: Topic :: Office/Business :: Financial :: Accounting
Classifier: Topic :: Utilities
Classifier: Environment :: Console
Classifier: Operating System :: OS Independent
Classifier: License :: OSI Approved :: GNU General Public License v3 (GPLv3)
